LICENSE
README.md
setup.py
galileo/__init__.py
galileo/framework/__init__.py
galileo/framework/libs/__init__.py
galileo/framework/libs/libbrpc.so
galileo/framework/libs/libclient.so
galileo/framework/libs/libgflags.so.2.2.2
galileo/framework/libs/libglog.so.0.4.0
galileo/framework/libs/libleveldb.so.1.22.0
galileo/framework/libs/libproto.so
galileo/framework/libs/libprotobuf.so.3.9.2.0
galileo/framework/libs/libprotoc.so.3.9.2.0
galileo/framework/libs/libzookeeper_mt.so.2.0.0
galileo/framework/python/__init__.py
galileo/framework/python/base_inputs.py
galileo/framework/python/base_message_passing.py
galileo/framework/python/base_module.py
galileo/framework/python/base_supervised.py
galileo/framework/python/base_trainer.py
galileo/framework/python/base_transform.py
galileo/framework/python/base_unsupervised.py
galileo/framework/python/client.py
galileo/framework/python/convert.py
galileo/framework/python/graph_meta.py
galileo/framework/python/named_object.py
galileo/framework/python/service.py
galileo/framework/python/utils/__init__.py
galileo/framework/python/utils/save_embedding.py
galileo/framework/python/utils/utils.py
galileo/framework/pytorch/__init__.py
galileo/framework/pytorch/kernel/entity_ops.cc
galileo/framework/pytorch/kernel/feature_ops.cc
galileo/framework/pytorch/kernel/neighbor_ops.cc
galileo/framework/pytorch/kernel/sequence_ops.cc
galileo/framework/pytorch/ops/ops.cc
galileo/framework/pytorch/python/__init__.py
galileo/framework/pytorch/python/losses.py
galileo/framework/pytorch/python/metrics.py
galileo/framework/pytorch/python/module.py
galileo/framework/pytorch/python/ops.py
galileo/framework/pytorch/python/supervised.py
galileo/framework/pytorch/python/trainer.py
galileo/framework/pytorch/python/unsupervised.py
galileo/framework/pytorch/python/utils.py
galileo/framework/pytorch/python/vertex_embedding.py
galileo/framework/pytorch/python/convolutions/__init__.py
galileo/framework/pytorch/python/convolutions/sage_layer.py
jdgalileo.egg-info/PKG-INFO
jdgalileo.egg-info/SOURCES.txt
jdgalileo.egg-info/dependency_links.txt
jdgalileo.egg-info/entry_points.txt
jdgalileo.egg-info/requires.txt
jdgalileo.egg-info/top_level.txt